[
  {
    "exercise_name": "log-and-order",
    "started_at": 1768407528.568945,
    "completed_at": 1768407530.230459,
    "comments": [],
    "status": "Completed"
  },
  {
    "exercise_name": "stage-fright",
    "started_at": 1768406580.155851,
    "completed_at": 1768406581.7284,
    "comments": [
      "Great work! You have successfully checked in all the actors!"
    ],
    "status": "Completed"
  },
  {
    "exercise_name": "under-control",
    "started_at": 1768406048.7249,
    "completed_at": 1768406050.114599,
    "comments": [
      "You successfully used git init to initialize this folder as a Git repository!"
    ],
    "status": "Completed"
  },
  {
    "exercise_name": "remote-control",
    "started_at": 1769072515.367295,
    "completed_at": 1769072577.312459,
    "comments": [
      "That is not the right Github url!"
    ],
    "status": "Incomplete"
  },
  {
    "exercise_name": "remote-control",
    "started_at": 1769072620.202276,
    "completed_at": 1769072626.535314,
    "comments": [
      "Great work setting up a public remote repository!"
    ],
    "status": "Completed"
  },
  {
    "exercise_name": "link-me",
    "started_at": 1769073029.721949,
    "completed_at": 1769073031.077682,
    "comments": [
      "Great work with using git remote to add an upstream remote!"
    ],
    "status": "Completed"
  },
  {
    "exercise_name": "push-over",
    "started_at": 1769074022.120191,
    "completed_at": 1769074024.039685,
    "comments": [
      "Great work pushing changes to the remote!"
    ],
    "status": "Completed"
  },
  {
    "exercise_name": "ignoring-somethings",
    "started_at": 1769074782.500391,
    "completed_at": 1769074786.174232,
    "comments": [
      "You are still ignoring why_am_i_hidden.txt. Find where the file is and fix that."
    ],
    "status": "Incomplete"
  },
  {
    "exercise_name": "ignoring-somethings",
    "started_at": 1769074838.683679,
    "completed_at": 1769074842.189245,
    "comments": [
      "You have not committed the relevant changes yet!"
    ],
    "status": "Incomplete"
  },
  {
    "exercise_name": "ignoring-somethings",
    "started_at": 1769074891.812531,
    "completed_at": 1769074893.968042,
    "comments": [
      "Great work using .gitignore!"
    ],
    "status": "Completed"
  },
  {
    "exercise_name": "clone-repo",
    "started_at": 1769082113.089504,
    "completed_at": 1769082116.359867,
    "comments": [
      "Great work creating a clone of a fork from Github!"
    ],
    "status": "Completed"
  },
  {
    "exercise_name": "fetch-and-pull",
    "started_at": 1769083419.037119,
    "completed_at": 1769083420.457783,
    "comments": [
      "Great work fetching and pulling different upstreams!"
    ],
    "status": "Completed"
  },
  {
    "exercise_name": "view-commits",
    "started_at": 1769099071.811976,
    "completed_at": 1769099074.107186,
    "comments": [
      "Great work in viewing and understanding the diff of a specific commit!"
    ],
    "status": "Completed"
  },
  {
    "exercise_name": "sensors-diff",
    "started_at": 1769100730.861763,
    "completed_at": 1769100734.967718,
    "comments": [
      "Answer for Which files have changed from Jan 09th to Jan 15th? does not contain all of the right answers."
    ],
    "status": "Incomplete"
  },
  {
    "exercise_name": "sensors-diff",
    "started_at": 1769100853.343414,
    "completed_at": 1769100854.896065,
    "comments": [
      "Great work comparing commits in git history!"
    ],
    "status": "Completed"
  },
  {
    "exercise_name": "sensors-checkout",
    "started_at": 1769101639.429965,
    "completed_at": 1769101640.725834,
    "comments": [
      "Great work traversing the revision history!"
    ],
    "status": "Completed"
  },
  {
    "exercise_name": "sensors-reset",
    "started_at": 1769106363.330972,
    "completed_at": 1769106366.346091,
    "comments": [
      "It seems like the commit from Jan 12 is still present in the commit history."
    ],
    "status": "Incomplete"
  },
  {
    "exercise_name": "sensors-reset",
    "started_at": 1769106459.513486,
    "completed_at": 1769106462.495571,
    "comments": [
      "It seems like the last two commits for Jan 14 and Jan 15 are still present in the commit history."
    ],
    "status": "Incomplete"
  },
  {
    "exercise_name": "side-track",
    "started_at": 1769498914.679973,
    "completed_at": 1769498916.669925,
    "comments": [
      "Great work with using git branch and git checkout to fix the bugs!"
    ],
    "status": "Completed"
  },
  {
    "exercise_name": "branch-previous",
    "started_at": 1769499402.604582,
    "completed_at": 1769499404.139413,
    "comments": [
      "Excellent work! You've successfully created branches from a previous commit and explored alternative storylines!"
    ],
    "status": "Completed"
  },
  {
    "exercise_name": "branch-bender",
    "started_at": 1769502199.743198,
    "completed_at": 1769502201.21451,
    "comments": [
      "Great work with merging the branches in order! Try running the HTML files locally!"
    ],
    "status": "Completed"
  },
  {
    "exercise_name": "branch-forward",
    "started_at": 1769502347.136604,
    "completed_at": 1769502348.577404,
    "comments": [
      "Great job fast-forward merging only 'with-sally'!"
    ],
    "status": "Completed"
  }
]